LICENSE
MANIFEST.in
README.md
requirements.txt
requirements_test.txt
setup.py
django_param/__init__.py
django_param/apps.py
django_param/forms.py
django_param/widget_map.py
django_param.egg-info/PKG-INFO
django_param.egg-info/SOURCES.txt
django_param.egg-info/dependency_links.txt
django_param.egg-info/not-zip-safe
django_param.egg-info/requires.txt
django_param.egg-info/top_level.txt
django_param/custom_field/__init__.py
django_param/custom_field/dataframe.py
django_param/custom_field/datepicker.py
django_param/custom_field/tuplefield.py
django_param/custom_widget/__init__.py
django_param/custom_widget/customcheckboxinput.py
django_param/custom_widget/dataframewidget.py
django_param/custom_widget/datepicker_widget.py
django_param/custom_widget/tuplefield_widget.py
django_param/migrations/__init__.py
django_param/static/django_param/dataframe/dataframe.css
django_param/static/django_param/dataframe/dataframe.js
django_param/static/django_param/datepicker/jquery.datetimepicker.full.js
django_param/static/django_param/datepicker/jquery.datetimepicker.full.min.js
django_param/static/django_param/datepicker/jquery.datetimepicker.min.css
django_param/static/django_param/datepicker/jquery.datetimepicker.min.js
django_param/templates/django_param/customcheckboxinput/customcheckboxinput_widget.html
django_param/templates/django_param/dataframe/dataframe.html
django_param/templates/django_param/datepicker/datepicker.html
django_param/templates/django_param/tuplefield/xytuplefield.html
django_param/utilities/helpers.py
tests/forms_tests.py
tests/widget_map_tests.py