Metadata-Version: 2.1
Name: django-param
Version: 0.1.10
Summary: Django Param provides the ParamForm class which translates a param class into a native Django Form.
Home-page: https://github.com/tethysplatform/django_param
Author: htran
Author-email: htran@aquaveo.com
License: BSD 2-Clause License
Platform: UNKNOWN
